Workbook
Name departements: gloabaltech_employees!$D$2:$D$151
Name pays: gloabaltech_employees!$J$2:$J$151
Name performance: gloabaltech_employees!$G$2:$G$151

Sheet Dashboard
B10: Les Tops 10 employés par performances
B11: Rang | C11: Nom et prenom | E11: Performance
B12: {=_xlfn.SEQUENCE(10)} -> 1 | C12: =_xlfn.XLOOKUP(E12,gloabaltech_employees!G:G,gloabaltech_employees!B:B) -> Christopher Garcia | E12: =LARGE(performance,Dashboard!B12) -> 4.99
B13: 2 | C13: =_xlfn.XLOOKUP(E13,gloabaltech_employees!G:G,gloabaltech_employees!B:B) -> Sandy Sanchez | E13: =LARGE(performance,Dashboard!B13) -> 4.98
B14: 3 | C14: =_xlfn.XLOOKUP(E14,gloabaltech_employees!G:G,gloabaltech_employees!B:B) -> Jennifer Calhoun | E14: =LARGE(performance,Dashboard!B14) -> 4.97
B15: 4 | C15: =_xlfn.XLOOKUP(E15,gloabaltech_employees!G:G,gloabaltech_employees!B:B) -> William Carpenter | E15: =LARGE(performance,Dashboard!B15) -> 4.96
B16: 5 | C16: =_xlfn.XLOOKUP(E16,gloabaltech_employees!G:G,gloabaltech_employees!B:B) -> Briana Mitchell | E16: =LARGE(performance,Dashboard!B16) -> 4.95
B17: 6 | C17: =_xlfn.XLOOKUP(E17,gloabaltech_employees!G:G,gloabaltech_employees!B:B) -> Stacey Hardy | E17: =LARGE(performance,Dashboard!B17) -> 4.94
B18: 7 | C18: =_xlfn.XLOOKUP(E18,gloabaltech_employees!G:G,gloabaltech_employees!B:B) -> James Green | E18: =LARGE(performance,Dashboard!B18) -> 4.93
B19: 8 | C19: =_xlfn.XLOOKUP(E19,gloabaltech_employees!G:G,gloabaltech_employees!B:B) -> Patricia Taylor | E19: =LARGE(performance,Dashboard!B19) -> 4.9
B20: 9 | C20: =_xlfn.XLOOKUP(E20,gloabaltech_employees!G:G,gloabaltech_employees!B:B) -> Amanda Newton | E20: =LARGE(performance,Dashboard!B20) -> 4.86
B21: 10 | C21: =_xlfn.XLOOKUP(E21,gloabaltech_employees!G:G,gloabaltech_employees!B:B) -> Beverly Washington | E21: =LARGE(performance,Dashboard!B21) -> 4.85

Sheet gloabaltech_employees
A1: ID Employé | B1: Nom | C1: Date d'embauche | D1: Département | E1: Poste | F1: Salaire (FCFA) | G1: Performance annuelle | H1: Jours de congé restants | I1: Statut du contrat | J1: Localisation
A2: 1 | B2: Michael Baker | C2: 43067 | D2: Support Client | E2: Responsable Service Client | F2: 37400 | G2: 3.9 | H2: 14 | I2: CDD | J2: France
A3: 2 | B3: Terry Davis | C3: 44368 | D3: Ventes | E3: Commercial | F3: 18720 | G3: 4.19 | H3: 8 | I3: CDD | J3: Espagne
A4: 3 | B4: Jane Baker | C4: 45049 | D4: Opérations | E4: Responsable Logistique | F4: 33480 | G4: 3.18 | H4: 9 | I4: Freelance | J4: Allemagne | M4: Nombre total d'employés | N4: =COUNTA(B2:B151) -> 150 | P4: Département | Q4: Nombre de personne | S4: Pays | T4: Nombre d'employé
A5: 4 | B5: Steven Fuller | C5: 44337 | D5: Opérations | E5: Responsable Logistique | F5: 47980 | G5: 3.35 | H5: 30 | I5: Freelance | J5: France | M5: Salaire Moyen par Employé | N5: =AVERAGE(F2:F151) -> 28678.333 | P5: {=_xlfn.UNIQUE(departements)} -> Support Client | Q5: =COUNTIF(departements,P5) -> 17 | S5: {=_xlfn.UNIQUE(pays)} -> France | T5: =COUNTIF(pays,S5) -> 32
A6: 5 | B6: Rachel Hartman | C6: 42816 | D6: Opérations | E6: Responsable Logistique | F6: 30400 | G6: 4.58 | H6: 12 | I6: CDI | J6: Italie | M6: Performance moyenne annuelle | N6: =AVERAGE(performance) -> 3.836 | P6: Ventes | Q6: =COUNTIF(departements,P6) -> 25 | S6: Espagne | T6: =COUNTIF(pays,S6) -> 32
A7: 6 | B7: Robert Erickson | C7: 43201 | D7: RH | E7: Gestionnaire RH | F7: 18900 | G7: 3.41 | H7: 2 | I7: Stage | J7: Italie | M7: Nombre moyen de jour de congé | N7: =AVERAGE(H2:H151) -> 15.733333 | P7: Opérations | Q7: =COUNTIF(departements,P7) -> 21 | S7: Allemagne | T7: =COUNTIF(pays,S7) -> 32
A8: 7 | B8: Juan Gomez | C8: 44443 | D8: Support Client | E8: Agent Support | F8: 27370 | G8: 3.79 | H8: 11 | I8: CDD | J8: Espagne | P8: RH | Q8: =COUNTIF(departements,P8) -> 21 | S8: Italie | T8: =COUNTIF(pays,S8) -> 34
A9: 8 | B9: Elizabeth Alexander | C9: 43023 | D9: RH | E9: Recruteur | F9: 11390 | G9: 2.79 | H9: 17 | I9: Stage | J9: Allemagne | P9: IT | Q9: =COUNTIF(departements,P9) -> 22 | S9: Belgique | T9: =COUNTIF(pays,S9) -> 20
A10: 9 | B10: Steve Ross | C10: 42352 | D10: IT | E10: Architecte Systèmes | F10: 48020 | G10: 4.26 | H10: 0 | I10: CDI | J10: Espagne | P10: Finance | Q10: =COUNTIF(departements,P10) -> 17
A11: 10 | B11: Terrance Cook | C11: 45193 | D11: Opérations | E11: Responsable Logistique | F11: 18800 | G11: 4.3 | H11: 14 | I11: Stage | J11: Espagne | P11: Marketing | Q11: =COUNTIF(departements,P11) -> 27
A12: 11 | B12: Tim Allen | C12: 43470 | D12: RH | E12: Recruteur | F12: 9950 | G12: 4.05 | H12: 8 | I12: CDI | J12: Espagne
A13: 12 | B13: Amanda Newton | C13: 42146 | D13: RH | E13: Responsable Paie | F13: 29290 | G13: 4.86 | H13: 19 | I13: CDI | J13: Allemagne
A14: 13 | B14: Joan Williams | C14: 43686 | D14: Ventes | E14: Commercial | F14: 24210 | G14: 3.59 | H14: 14 | I14: Stage | J14: Allemagne
A15: 14 | B15: John Hernandez | C15: 42565 | D15: RH | E15: Recruteur | F15: 12630 | G15: 4.78 | H15: 5 | I15: Freelance | J15: France
A16: 15 | B16: Lisa Murphy | C16: 44741 | D16: Finance | E16: Contrôleur de Gestion | F16: 38250 | G16: 3.22 | H16: 17 | I16: CDI | J16: Italie
A17: 16 | B17: Debra Cox | C17: 42256 | D17: Support Client | E17: Agent Support | F17: 41370 | G17: 4.46 | H17: 23 | I17: Freelance | J17: Espagne
A18: 17 | B18: Michael Lawson | C18: 44940 | D18: Support Client | E18: Agent Support | F18: 23910 | G18: 3.02 | H18: 23 | I18: Stage | J18: France
A19: 18 | B19: Sally Johnson | C19: 43557 | D19: Marketing | E19: Community Manager | F19: 32640 | G19: 3.27 | H19: 2 | I19: CDI | J19: Allemagne
A20: 19 | B20: Katherine Barnes | C20: 42843 | D20: IT | E20: Admin Réseau | F20: 37280 | G20: 4.51 | H20: 27 | I20: Freelance | J20: Espagne
A21: 20 | B21: Kayla Banks | C21: 44891 | D21: RH | E21: Recruteur | F21: 34640 | G21: 3.81 | H21: 5 | I21: CDI | J21: France
A22: 21 | B22: Sean Rosales | C22: 42835 | D22: Marketing | E22: Responsable Marketing | F22: 13140 | G22: 4.8 | H22: 16 | I22: Freelance | J22: Belgique
A23: 22 | B23: Lee Williams | C23: 42668 | D23: Ventes | E23: Commercial | F23: 20500 | G23: 2.65 | H23: 16 | I23: CDI | J23: Belgique
... A151: 150 | B151: Randy Daniels MD | C151: 43742 | D151: Finance | E151: Analyste Financier | F151: 32210 | G151: 4.85 | H151: 2 | I151: CDI | J151: Italie

Sheet 1- Colonne
A1: Résumé Revenu GlobalTechSolution 2025
B3: Ordinateur | C3: Téléphone | D3: Tablette
A4: Entrées | B4: 82837 | C4: 93291 | D4: 75682
A5: Sorties | B5: 57190 | C5: 49726 | D5: 62645
A6: Profit/Perte | B6: =B4-B5 -> 25647 | C6: =C4-C5 -> 43565 | D6: =D4-D5 -> 13037

Sheet 2- Barre
A1: Durée de produits en entreprise
A3: Produit | B3: Durée de conservation (jours) | C3: Temps de réapprovisionnement (jours)
A4: Poires | B4: 6 | C4: 8
A5: Bananes | B5: 5 | C5: 12
A6: Oranges | B6: 9 | C6: 7
A7: Pommes | B7: 18 | C7: 10

Sheet 3- Ligne
A1: Tendance de vente par Mois
A3: Mois | B3: Ordinateurs de bureau (Desktops) | C3: Ordinateurs portables (Laptops) | D3: Tablettes (Tablets)
A4: Janvier | B4: 80 | C4: 30 | D4: 10
A5: Février | B5: 50 | C5: 28 | D5: 15
A6: Mars | B6: 30 | C6: 35 | D6: 25
A7: Avril | B7: 20 | C7: 45 | D7: 40
A8: Mai | B8: 15 | C8: 43 | D8: 60
A9: Juin | B9: 10 | C9: 50 | D9: 90

Sheet 4- Aires
A1: Analyse Ordre de Ventes
A3: Mois | B3: Mobile | C3: TV | D3: Batterie | E3: Chargeur | F3: Câble
A4: Jan | B4: 10 | C4: 12 | D4: 8 | E4: 14 | F4: 15
A5: Fév | B5: 15 | C5: 14 | D5: 9 | E5: 16 | F5: 18
A6: Mar | B6: 20 | C6: 16 | D6: 10 | E6: 18 | F6: 22
A7: Avr | B7: 18 | C7: 18 | D7: 12 | E7: 20 | F7: 24
A8: Mai | B8: 22 | C8: 20 | D8: 13 | E8: 22 | F8: 26
A9: Juin | B9: 25 | C9: 22 | D9: 15 | E9: 24 | F9: 28
A10: Juil | B10: 28 | C10: 25 | D10: 18 | E10: 26 | F10: 30
A11: Août | B11: 30 | C11: 27 | D11: 20 | E11: 28 | F11: 32
A12: Sept | B12: 27 | C12: 26 | D12: 19 | E12: 27 | F12: 31
A13: Oct | B13: 25 | C13: 24 | D13: 18 | E13: 25 | F13: 30
A14: Nov | B14: 22 | C14: 22 | D14: 17 | E14: 23 | F14: 28
A15: Déc | B15: 20 | C15: 20 | D15: 15 | E15: 22 | F15: 26

Sheet 5- Secteur (Camembert)
A1: Réparatition des ventes par produit
A3: Produit | B3: Ventes
A4: Produit A | B4: 100
A5: Produit B | B5: 75
A6: Produit C | B6: 50
A7: Produit D | B7: 25

Sheet 6- Nuages de points
A1: Objets vendus
A3: Nb vendus | B3: Montant
A4: 15 | B4: 45
A5: 18 | B5: 46
A6: 20 | B6: 44
A7: 22 | B7: 48
A8: 25 | B8: 52
A9: 30 | B9: 58
A10: 35 | B10: 72
A11: 38 | B11: 85
A12: 40 | B12: 90
A13: 43 | B13: 94
A14: 45 | B14: 97
A15: 48 | B15: 100
A16: 50 | B16: 102

Sheet 7- Bulles
A1: Ventes de produits dans différents magasins
A3: Magasin | B3: Nombre de clients | C3: Produits vendus | D3: Chiffre d'affaires ($)
A4: A | B4: 10 | C4: 5 | D4: 300
A5: B | B5: 15 | C5: 10 | D5: 600
A6: C | B6: 20 | C6: 8 | D6: 200
A7: D | B7: 25 | C7: 15 | D7: 400
A8: E | B8: 30 | C8: 12 | D8: 500
A9: F | B9: 35 | C9: 18 | D9: 700
A10: G | B10: 40 | C10: 20 | D10: 900
A11: H | B11: 45 | C11: 25 | D11: 1200
A12: I | B12: 50 | C12: 22 | D12: 1100
A13: J | B13: 55 | C13: 17 | D13: 800
A14: K | B14: 60 | C14: 14 | D14: 600
A15: L | B15: 65 | C15: 19 | D15: 700
... A17: N | B17: 75 | C17: 26 | D17: 300

Sheet Radar
A1: Notes obtenues par étudiants
A3: Étudiant | B3: Biologie | C3: Physique | D3: Maths | E3: Sport | F3: Anglais | G3: Français | H3: Histoire
A4: Etudiant 1 | B4: 19 | C4: 9 | D4: 13 | E4: 16 | F4: 6 | G4: 6 | H4: 8
A5: Etudiant 2 | B5: 20 | C5: 14 | D5: 11 | E5: 13 | F5: 5 | G5: 17 | H5: 14
A6: Etudiant 3 | B6: 18 | C6: 19 | D6: 19 | E6: 12 | F6: 7 | G6: 10 | H6: 10
A7: Etudiant 4 | B7: 13 | C7: 14 | D7: 11 | E7: 18 | F7: 15 | G7: 20 | H7: 15
A8: Etudiant 5 | B8: 7 | C8: 20 | D8: 19 | E8: 5 | F8: 10 | G8: 17 | H8: 18
A9: Moyenne | B9: =AVERAGE(B4:B8) -> 15.4 | C9: =AVERAGE(C4:C8) -> 15.2 | D9: =AVERAGE(D4:D8) -> 14.6 | E9: =AVERAGE(E4:E8) -> 12.8 | F9: =AVERAGE(F4:F8) -> 8.6 | G9: =AVERAGE(G4:G8) -> 14 | H9: =AVERAGE(H4:H8) -> 13

Sheet 9- Cascade
A1: Evolution des ventes mensuelles au cours de l'année
A3: Mois | B3: Variation des ventes
A4: Début | B4: 4000
A5: Janvier | B5: 1707
A6: Février | B6: 1425
A7: Mars | B7: -1050
A8: Avril | B8: 1812
A9: Mai | B9: -1067
A10: Juin | B10: -1481
A11: Juillet | B11: 1228
A12: Août | B12: 1176
A13: Septembre | B13: 1146
A14: Octobre | B14: 1209
A15: Novembre | B15: -1588
... A17: Fin | B17: 4000

Sheet 10- Histogramme
A1: Comparaison des quantités produites
A3: Produit | B3: Trim 1 | C3: Trim 2 | D3: Trim 3 | E3: Trim 4 | F3: Total
A4: Compote | B4: 27118 | C4: 7467 | D4: 13194 | E4: 22814 | F4: 70593
A5: Confiture | B5: 25232 | C5: 31275 | D5: 38540 | E5: 42853 | F5: 137897
A6: Marmelade | B6: 21854 | C6: 24860 | D6: 24180 | E6: 27863 | F6: 98757

Sheet 11- Carte
A1: Population par pays
A3: Pays | B3: Population (millions)
A4: États-Unis | B4: 331
A5: Canada | B5: 38
A6: Brésil | B6: 213
A7: Russie | B7: 144
A8: Chine | B8: 1412
A9: Inde | B9: 1393
A10: Australie | B10: 26
A11: France | B11: 67
A12: Allemagne | B12: 83
A13: Royaume-Uni | B13: 68
A14: Afrique du Sud | B14: 60
A15: Nigéria | B15: 206
... A19: Indonésie | B19: 276

Sheet 12- Treemap
A1: Ventes de repas
A3: Repas | B3: Catégorie | C3: Produit | D3: Prix (USD) | E3: Quantité | F3: Profit (USD)
A4: Petit-déjeuner | B4: Boisson | C4: Café | D4: 1 | E4: 20 | F4: 20
A5: Petit-déjeuner | B5: Boisson | C5: Thé | D5: 1 | E5: 5 | F5: 5
A6: Petit-déjeuner | B6: Aliment | C6: Gaufre | D6: 1 | E6: 5 | F6: 5
A7: Petit-déjeuner | B7: Aliment | C7: Pancakes | D7: 2 | E7: 10 | F7: 20
A8: Petit-déjeuner | B8: Aliment | C8: Œufs | D8: 2 | E8: 7 | F8: 14
A9: Déjeuner | B9: Boisson | C9: Thé glacé | D9: 2 | E9: 12 | F9: 24
A10: Déjeuner | B10: Aliment | C10: Soupe | D10: 3 | E10: 5 | F10: 15
A11: Déjeuner | B11: Aliment | C11: Sandwich | D11: 5 | E11: 10 | F11: 50
A12: Déjeuner | B12: Aliment | C12: Salade | D12: 5 | E12: 5 | F12: 25
A13: Déjeuner | B13: Aliment | C13: Tarte | D13: 4 | E13: 5 | F13: 20
A14: Déjeuner | B14: Aliment | C14: Cookie | D14: 3 | E14: 10 | F14: 30
A15: Dîner | B15: Boisson | C15: Café | D15: 2 | E15: 10 | F15: 20
... A18: Dîner | B18: Aliment | C18: Salade | D18: 5 | E18: 10 | F18: 50

Sheet 13- Entonnoir (Funnel)
A1: Pipeline de vente
A3: Étape | B3: Montant
A4: Prospects | B4: 500
A5: Prospects qualifiés | B5: 425
A6: Analyse des besoins | B6: 200
A7: Devis | B7: 150
A8: Négociations | B8: 100
A9: Ventes conclues | B9: 90

Sheet 14- Combinaison
A1: Ventes 2024
A3: Mois | B3: Objectif prévisionnel | C3: Réel
A4: Janvier | B4: 200 | C4: 200
A5: Février | B5: 200 | C5: 180
A6: Mars | B6: 150 | C6: 100
A7: Avril | B7: 220 | C7: 250
A8: Mai | B8: 230 | C8: 180
A9: Juin | B9: 250 | C9: 140
A10: Juillet | B10: 200 | C10: 160
A11: Août | B11: 260 | C11: 155
A12: Septembre | B12: 270 | C12: 170
A13: Octobre | B13: 290 | C13: 150
A14: Novembre | B14: 190 | C14: 180
A15: Décembre | B15: 300 | C15: 250
